django_anexia_sms_gateway/__init__.py
django_anexia_sms_gateway/sms.py
django_anexia_sms_gateway-1.1.0.dist-info/LICENSE
django_anexia_sms_gateway-1.1.0.dist-info/METADATA
django_anexia_sms_gateway-1.1.0.dist-info/WHEEL
django_anexia_sms_gateway-1.1.0.dist-info/top_level.txt
django_anexia_sms_gateway-1.1.0.dist-info/RECORD
