Metadata-Version: 2.1
Name: django-anexia-sms-gateway
Version: 1.1.0
Summary: A django module that allows to send short messages via the Anexia SMS gateway
Home-page: https://github.com/anexia/django-anexia-sms-gateway
Author: Alexandra Bruckner
Author-email: abruckner@anexia-it.com
License: MIT License
Classifier: Development Status :: 5 - Production/Stable
Classifier: Framework :: Django
Classifier: Framework :: Django :: 2.2
Classifier: Framework :: Django :: 3.1
Classifier: Framework :: Django :: 3.2
Classifier: Framework :: Django :: 4.2
Classifier: Intended Audience :: Developers
Classifier: License :: OSI Approved :: MIT License
Classifier: Operating System :: OS Independent
Classifier: Programming Language :: Python
Classifier: Programming Language :: Python :: 3
Classifier: Programming Language :: Python :: 3.8
Classifier: Programming Language :: Python :: 3.9
Classifier: Programming Language :: Python :: 3.10
Classifier: Programming Language :: Python :: 3.11
License-File: LICENSE
